CHANGES.rst
CONTRIBUTORS.rst
LATEST
MANIFEST.in
README.rst
setup.cfg
setup.py
docs/index.rst
docs/license.rst
docs/about/communication.rst
docs/about/history.rst
docs/about/index.rst
docs/about/roadmap.rst
docs/api/modules.rst
docs/api/ploneintranet.activitystream.Extensions.rst
docs/api/ploneintranet.activitystream.browser.rst
docs/api/ploneintranet.activitystream.browser.tiles.rst
docs/api/ploneintranet.activitystream.rst
docs/api/ploneintranet.activitystream.tests.rst
docs/api/ploneintranet.api.microblog.rst
docs/api/ploneintranet.api.rst
docs/api/ploneintranet.api.tests.rst
docs/api/ploneintranet.attachments.browser.rst
docs/api/ploneintranet.attachments.rst
docs/api/ploneintranet.attachments.tests.rst
docs/api/ploneintranet.core.browser.rst
docs/api/ploneintranet.core.browser.tiles.rst
docs/api/ploneintranet.core.rst
docs/api/ploneintranet.core.tests.rst
docs/api/ploneintranet.docconv.client.rst
docs/api/ploneintranet.docconv.client.tests.rst
docs/api/ploneintranet.docconv.rst
docs/api/ploneintranet.invitations.rst
docs/api/ploneintranet.invitations.tests.rst
docs/api/ploneintranet.layout.rst
docs/api/ploneintranet.layout.viewlets.rst
docs/api/ploneintranet.messaging.Extensions.rst
docs/api/ploneintranet.messaging.browser.rst
docs/api/ploneintranet.messaging.rst
docs/api/ploneintranet.messaging.tests.rst
docs/api/ploneintranet.microblog.browser.rst
docs/api/ploneintranet.microblog.browser.tiles.rst
docs/api/ploneintranet.microblog.rst
docs/api/ploneintranet.microblog.tests.rst
docs/api/ploneintranet.network.Extensions.rst
docs/api/ploneintranet.network.browser.rst
docs/api/ploneintranet.network.rst
docs/api/ploneintranet.network.tests.rst
docs/api/ploneintranet.notifications.adapters.rst
docs/api/ploneintranet.notifications.browser.rst
docs/api/ploneintranet.notifications.events.rst
docs/api/ploneintranet.notifications.rst
docs/api/ploneintranet.notifications.tests.rst
docs/api/ploneintranet.pagerank.rst
docs/api/ploneintranet.pagerank.tests.rst
src/ploneintranet.egg-info/PKG-INFO
src/ploneintranet.egg-info/SOURCES.txt
src/ploneintranet.egg-info/dependency_links.txt
src/ploneintranet.egg-info/entry_points.txt
src/ploneintranet.egg-info/namespace_packages.txt
src/ploneintranet.egg-info/not-zip-safe
src/ploneintranet.egg-info/requires.txt
src/ploneintranet.egg-info/top_level.txt
