Metadata-Version: 1.1
Name: ploneintranet
Version: 1.1.2
Summary: Intranet suite for Plone
Home-page: https://github.com/ploneintranet/ploneintranet
Author: Plone Intranet Consortium
Author-email: info@ploneintranet.org
License: gpl
Keywords: intranet social activitystream collaboration groupware
Platform: UNKNOWN
Classifier: Environment :: Web Environment
Classifier: Framework :: Plone
Classifier: Framework :: Plone :: 5.0
Classifier: License :: OSI Approved :: GNU General Public License v2 (GPLv2)
Classifier: Operating System :: OS Independent
Classifier: Programming Language :: Python
Classifier: Programming Language :: Python :: 2.7
Classifier: Topic :: Office/Business
Classifier: Topic :: Office/Business :: Groupware
Classifier: Topic :: Software Development :: Libraries :: Python Modules
Classifier: License :: OSI Approved :: GNU General Public License v2 (GPLv2)
